Equation_Solver_Pro/Equation_Solver_Pro.py
Equation_Solver_Pro/__init__.py
equation_solver_pro-0.1.dist-info/LICENSE.txt
equation_solver_pro-0.1.dist-info/METADATA
equation_solver_pro-0.1.dist-info/WHEEL
equation_solver_pro-0.1.dist-info/top_level.txt
equation_solver_pro-0.1.dist-info/RECORD
